athena_mcp/__init__.py
athena_mcp/athena.py
athena_mcp/config.py
athena_mcp/models.py
athena_mcp/server.py
athena_mcp/tools/__init__.py
athena_mcp/tools/query.py
athena_mcp/tools/schema.py
aws_athena_mcp-1.0.1.dist-info/licenses/LICENSE
aws_athena_mcp-1.0.1.dist-info/METADATA
aws_athena_mcp-1.0.1.dist-info/WHEEL
aws_athena_mcp-1.0.1.dist-info/entry_points.txt
aws_athena_mcp-1.0.1.dist-info/top_level.txt
aws_athena_mcp-1.0.1.dist-info/RECORD
