Metadata-Version: 2.4
Name: aws-athena-mcp
Version: 1.0.1
Summary: A simple, clean MCP server for AWS Athena integration
Author: AWS Athena MCP Contributors
License: MIT
Project-URL: Homepage, https://github.com/ColeMurray/aws-athena-mcp
Project-URL: Repository, https://github.com/ColeMurray/aws-athena-mcp
Project-URL: Issues, https://github.com/ColeMurray/aws-athena-mcp/issues
Project-URL: Documentation, https://github.com/ColeMurray/aws-athena-mcp#readme
Project-URL: Changelog, https://github.com/ColeMurray/aws-athena-mcp/blob/main/CHANGELOG.md
Classifier: Development Status :: 4 - Beta
Classifier: Intended Audience :: Developers
Classifier: License :: OSI Approved :: MIT License
Classifier: Programming Language :: Python :: 3
Classifier: Programming Language :: Python :: 3.10
Classifier: Programming Language :: Python :: 3.11
Classifier: Programming Language :: Python :: 3.12
Classifier: Topic :: Database
Classifier: Topic :: Software Development :: Libraries :: Python Modules
Requires-Python: >=3.10
License-File: LICENSE
Requires-Dist: fastmcp==2.5.2
Requires-Dist: boto3<2.0.0,>=1.34.0
Requires-Dist: pydantic<3.0.0,>=2.5.0
Provides-Extra: dev
Requires-Dist: pytest<8.0.0,>=7.4.0; extra == "dev"
Requires-Dist: pytest-asyncio<1.0.0,>=0.21.0; extra == "dev"
Requires-Dist: pytest-cov<5.0.0,>=4.1.0; extra == "dev"
Requires-Dist: black<24.0.0,>=23.12.0; extra == "dev"
Requires-Dist: isort<6.0.0,>=5.13.0; extra == "dev"
Requires-Dist: mypy<2.0.0,>=1.8.0; extra == "dev"
Requires-Dist: moto[athena]<5.0.0,>=4.2.0; extra == "dev"
Requires-Dist: types-boto3<2.0.0,>=1.0.0; extra == "dev"
Dynamic: license-file
